app/__init__.py
app/config.yml
restylinchpin-0.1.0.dist-info/LICENSE
restylinchpin-0.1.0.dist-info/METADATA
restylinchpin-0.1.0.dist-info/WHEEL
restylinchpin-0.1.0.dist-info/top_level.txt
restylinchpin-0.1.0.dist-info/RECORD
